LICENSE
README.md
setup.py
.github/ISSUE_TEMPLATE/bug_report.md
.github/ISSUE_TEMPLATE/feature_request.md
examples/Aufnahme.py
examples/GuitarNoteA.ipynb
examples/GuitarNoteA.py
examples/Record.py
examples/Registrazione.py
examples/Saw.py
examples/WineGlass.ipynb
examples/WineGlass.py
examples/audioFiles/A-Saite.wav
examples/audioFiles/SawBlockCut1.m4a
examples/audioFiles/SawBlockCut2.m4a
examples/audioFiles/SawBoardCut1.m4a
examples/audioFiles/SawBoardCut2.m4a
examples/audioFiles/SawUnloaded.m4a
examples/audioFiles/WineGlass.wav
pyAudioAnalyzer/AudioAnalyzer.py
pyAudioAnalyzer/AudioAnalyzer.pyNew
pyAudioAnalyzer/KlappeSimFilter.wav
pyAudioAnalyzer/KlappeSimFilter2000.wav
pyAudioAnalyzer/__init__.py
pyAudioAnalyzer/abc.png
pyAudioAnalyzer/abc.svg
pyAudioAnalyzer.egg-info/PKG-INFO
pyAudioAnalyzer.egg-info/SOURCES.txt
pyAudioAnalyzer.egg-info/dependency_links.txt
pyAudioAnalyzer.egg-info/requires.txt
pyAudioAnalyzer.egg-info/top_level.txt
pyAudioAnalyzer/__pycache__/AnalyzeSound.cpython-39.pyc
pyAudioAnalyzer/__pycache__/AnalyzeSoundNew.cpython-39.pyc
pyAudioAnalyzer/__pycache__/AudioAnalyzer.cpython-39.pyc
pyAudioAnalyzer/__pycache__/__init__.cpython-39.pyc