Metadata-Version: 2.1
Name: pyAudioAnalyzer
Version: 0.2.2
Summary: Python library for vibrational analysis of audio
Home-page: https://github.com/e-dub/pyAudioAnalyzer
Author: E. J. Wehrle
License: gpl-3.0
Platform: UNKNOWN
License-File: LICENSE
